mcpf_metapackage/meta/__init__.py
mcpf-0.1.0.post1.dist-info/LICENSE
mcpf-0.1.0.post1.dist-info/METADATA
mcpf-0.1.0.post1.dist-info/WHEEL
mcpf-0.1.0.post1.dist-info/RECORD
